torchshard/__init__.py
torchshard/_tensor.py
torchshard/overrides.py
torchshard/serialization.py
torchshard/utils.py
torchshard/distributed/__init__.py
torchshard/distributed/comm.py
torchshard/distributed/core.py
torchshard/nn/__init__.py
torchshard/nn/_reduction.py
torchshard/nn/functional.py
torchshard/nn/init.py
torchshard/nn/modules/__init__.py
torchshard/nn/modules/linear.py
torchshard/nn/modules/loss.py
torchshard/nn/modules/sparse.py
torchshard-0.1.0.dist-info/LICENSE
torchshard-0.1.0.dist-info/METADATA
torchshard-0.1.0.dist-info/WHEEL
torchshard-0.1.0.dist-info/top_level.txt
torchshard-0.1.0.dist-info/RECORD
